abis/AccountFacet.json
abis/ERC20.json
abis/MarketFacet.json
abis/OrderFacet.json
abis/PositionFacet.json
abis/__init__.py
clients/__init__.py
clients/client.py
clients/configs.py
clients/keys.py
clients/utils.py
examples/__init__.py
examples/example_config.py
examples/get_market.py
examples/get_market_arbitrum.py
examples/get_market_base.py
examples/open_close_cross_position.py
examples/open_close_cross_position_arbitrum.py
examples/open_close_cross_position_base.py
examples/open_close_degen_arbitrum.py
examples/open_close_degen_base.py
examples/open_close_isolate_position.py
examples/open_close_isolate_position_arbitrum.py
elfi_python_sdk-1.0.9.dist-info/METADATA
elfi_python_sdk-1.0.9.dist-info/WHEEL
elfi_python_sdk-1.0.9.dist-info/top_level.txt
elfi_python_sdk-1.0.9.dist-info/RECORD
